helusers/__init__.py
helusers/_oidc_auth_impl.py
helusers/_rest_framework_jwt_impl.py
helusers/adapter.py
helusers/admin.py
helusers/admin_site.py
helusers/apps.py
helusers/authz.py
helusers/context_processors.py
helusers/defaults.py
helusers/jwt.py
helusers/models.py
helusers/oidc.py
helusers/pipeline.py
helusers/settings.py
helusers/tunnistamo_oidc.py
helusers/urls.py
helusers/user_utils.py
helusers/utils.py
helusers/views.py
helusers/locale/fi/LC_MESSAGES/django.po
helusers/management/commands/sync_helusers.py
helusers/migrations/0001_add_ad_groups.py
helusers/migrations/0002_add_oidcbackchannellogoutevent.py
helusers/migrations/__init__.py
helusers/providers/__init__.py
helusers/providers/helsinki/__init__.py
helusers/providers/helsinki/admin.py
helusers/providers/helsinki/models.py
helusers/providers/helsinki/provider.py
helusers/providers/helsinki/urls.py
helusers/providers/helsinki/views.py
helusers/providers/helsinki_oidc/__init__.py
helusers/providers/helsinki_oidc/admin.py
helusers/providers/helsinki_oidc/models.py
helusers/providers/helsinki_oidc/provider.py
helusers/providers/helsinki_oidc/urls.py
helusers/providers/helsinki_oidc/views.py
helusers/templates/admin/base_site.html
helusers/templates/admin/base_site_default.html
helusers/templates/admin/base_site_grappelli.html
helusers/templates/admin/hel_login.html
django_helusers_turku-1.0.0.dist-info/LICENSE
django_helusers_turku-1.0.0.dist-info/METADATA
django_helusers_turku-1.0.0.dist-info/WHEEL
django_helusers_turku-1.0.0.dist-info/top_level.txt
django_helusers_turku-1.0.0.dist-info/RECORD
