Metadata-Version: 2.1
Name: django-helusers-turku
Version: 1.0.0
Summary: Django app for the user infrastructure of the City of Turku
Home-page: https://github.com/City-of-Turku/django-helusers
Author: City of Turku
Author-email: sovellustuki@turku.fi
License: BSD License
Classifier: Environment :: Web Environment
Classifier: Framework :: Django
Classifier: Intended Audience :: Developers
Classifier: License :: OSI Approved :: BSD License
Classifier: Operating System :: OS Independent
Classifier: Programming Language :: Python
Classifier: Programming Language :: Python :: 3
Classifier: Programming Language :: Python :: 3.6
Classifier: Programming Language :: Python :: 3.7
Classifier: Programming Language :: Python :: 3.8
Classifier: Programming Language :: Python :: 3.9
Classifier: Topic :: Internet :: WWW/HTTP
Classifier: Topic :: Internet :: WWW/HTTP :: Dynamic Content
License-File: LICENSE
Requires-Dist: Django (<4,>=2.2)
Requires-Dist: cachetools (>=3.0.0)
Requires-Dist: deprecation (>=2)
Requires-Dist: requests
Requires-Dist: python-jose
